[{"Materias": [
    {"id":0,
     "nombre": "Todas"
    },
    {"id":1,
     "nombre": "Matematica"
    },
    {"id":2,
     "nombre": "Musica"
    },
    {"id":3,
     "nombre": "Programacion"
    },
    {"id":4,
     "nombre": "Fotografia"
    }
]},
{
    "tipoClase":[
        {"id":0,
        "nombre": "Todas"
        },        
        {"id":1,
         "nombre": "Grupal"
        },
        {"id":2,
         "nombre": "Individual"
        }
    ]
},
{
    "frecuencia":[
        {"id":0,
        "nombre": "Todas"
        },        
        {"id":1,
         "nombre": "Unica"
        },
        {"id":2,
         "nombre": "Semanal"
        },
        {"id":3,
         "nombre":"Mensual"      
        }
    ]
},
{
    "Calificacion":[
        {"id":0,
        "nombre": "Todas"
        },        
        {"id":1,
         "nombre": 1
        },
        {"id":2,
         "nombre": 2
        },
        {"id":3,
         "nombre": 3      
        },
        {"id":4,
         "nombre": 4
        },
        {"id":5,
         "nombre": 5
        } 
    ]
}
]